README.md
setup.py
gnucash_ixbrl/__init__.py
gnucash_ixbrl/accounts.py
gnucash_ixbrl/accounts_gnucash.py
gnucash_ixbrl/accounts_piecash.py
gnucash_ixbrl/basicelement.py
gnucash_ixbrl/composite.py
gnucash_ixbrl/computation.py
gnucash_ixbrl/config.py
gnucash_ixbrl/context.py
gnucash_ixbrl/dataset.py
gnucash_ixbrl/datasource.py
gnucash_ixbrl/datum.py
gnucash_ixbrl/element.py
gnucash_ixbrl/fact.py
gnucash_ixbrl/facttable.py
gnucash_ixbrl/format.py
gnucash_ixbrl/html.py
gnucash_ixbrl/multi_period.py
gnucash_ixbrl/note_parse.py
gnucash_ixbrl/notes.py
gnucash_ixbrl/page.py
gnucash_ixbrl/period.py
gnucash_ixbrl/report.py
gnucash_ixbrl/taxonomy.py
gnucash_ixbrl/title.py
gnucash_ixbrl/valueset.py
gnucash_ixbrl/worksheet_ixbrl.py
gnucash_ixbrl/worksheet_model.py
gnucash_ixbrl/worksheetelement.py
gnucash_ixbrl.egg-info/PKG-INFO
gnucash_ixbrl.egg-info/SOURCES.txt
gnucash_ixbrl.egg-info/dependency_links.txt
gnucash_ixbrl.egg-info/requires.txt
gnucash_ixbrl.egg-info/top_level.txt
scripts/gnucash-ixbrl