Metadata-Version: 2.1
Name: gnucash-ixbrl
Version: 1.7.0
Summary: Production of iXBRL reports from GnuCash accounts
Home-page: https://github.com/cybermaggedon/gnucash-ixbrl
Author: Cybermaggedon
Author-email: mark@cyberapocalypse.co.uk
License: UNKNOWN
Download-URL: https://github.com/cybermaggedon/gnucash-ixbrl/archive/refs/tags/v1.7.0.tar.gz
Platform: UNKNOWN
Classifier: Programming Language :: Python :: 3
Classifier: License :: OSI Approved :: GNU General Public License v3 or later (GPLv3+)
Classifier: Operating System :: OS Independent
Requires-Python: >=3.6
